pyEDAA/Reports/__init__.py
pyEDAA/Reports/py.typed
pyEDAA/Reports/CLI/Unittesting.py
pyEDAA/Reports/CLI/__init__.py
pyEDAA/Reports/Dependency/__init__.py
pyEDAA/Reports/DocumentationCoverage/Python.py
pyEDAA/Reports/DocumentationCoverage/__init__.py
pyEDAA/Reports/Requirement/Python.py
pyEDAA/Reports/Requirement/__init__.py
pyEDAA/Reports/Resources/Ant-JUnit4.xsd
pyEDAA/Reports/Resources/Any-JUnit.xsd
pyEDAA/Reports/Resources/CTest-JUnit.xsd
pyEDAA/Reports/Resources/GoogleTest-JUnit.xsd
pyEDAA/Reports/Resources/PyTest-JUnit.xsd
pyEDAA/Reports/Resources/__init__.py
pyEDAA/Reports/Unittesting/__init__.py
pyEDAA/Reports/Unittesting/JUnit/AntJUnit4.py
pyEDAA/Reports/Unittesting/JUnit/CTestJUnit.py
pyEDAA/Reports/Unittesting/JUnit/GoogleTestJUnit.py
pyEDAA/Reports/Unittesting/JUnit/PyTestJUnit.py
pyEDAA/Reports/Unittesting/JUnit/__init__.py
pyedaa_reports-0.17.0.dist-info/licenses/LICENSE.md
pyedaa_reports-0.17.0.dist-info/METADATA
pyedaa_reports-0.17.0.dist-info/WHEEL
pyedaa_reports-0.17.0.dist-info/entry_points.txt
pyedaa_reports-0.17.0.dist-info/top_level.txt
pyedaa_reports-0.17.0.dist-info/RECORD
