Metadata-Version: 2.4
Name: pyEDAA.Reports
Version: 0.17.0
Summary: Various report abstract data models and report format converters.
Home-page: https://GitHub.com/pyEDAA/pyEDAA.Reports
Author: Patrick Lehmann
Author-email: Paebbels@gmail.com
License: Apache-2.0
Project-URL: Documentation, https://pyEDAA.GitHub.io/pyEDAA.Reports
Project-URL: Source Code, https://GitHub.com/pyEDAA/pyEDAA.Reports
Project-URL: Issue Tracker, https://GitHub.com/pyEDAA/pyEDAA.Reports/issues
Keywords: Reports,Abstract Model,Data Model,Unit Testing,Testcase,Testsuite,OSVVM,YAML,XML
Classifier: Operating System :: OS Independent
Classifier: Intended Audience :: Developers
Classifier: Topic :: Utilities
Classifier: Topic :: Scientific/Engineering :: Electronic Design Automation (EDA)
Classifier: License :: OSI Approved :: Apache Software License
Classifier: Programming Language :: Python :: 3 :: Only
Classifier: Programming Language :: Python :: 3.9
Classifier: Programming Language :: Python :: 3.10
Classifier: Programming Language :: Python :: 3.11
Classifier: Programming Language :: Python :: 3.12
Classifier: Programming Language :: Python :: 3.13
Classifier: Development Status :: 4 - Beta
Requires-Python: >=3.9
License-File: LICENSE.md
Requires-Dist: lxml~=5.4
Requires-Dist: ruamel.yaml~=0.18
Requires-Dist: pyTooling<9.0,>=6.7
Provides-Extra: doc
Requires-Dist: lxml~=5.4; extra == "doc"
Requires-Dist: sphinx~=8.2; extra == "doc"
Requires-Dist: autoapi>=2.0.1; extra == "doc"
Requires-Dist: sphinx_autodoc_typehints~=3.2; extra == "doc"
Requires-Dist: sphinx-copybutton>=0.5.2; extra == "doc"
Requires-Dist: sphinx_reports~=0.9; extra == "doc"
Requires-Dist: pyTooling<9.0,>=6.7; extra == "doc"
Requires-Dist: sphinxcontrib-mermaid~=1.0; extra == "doc"
Requires-Dist: ruamel.yaml~=0.18; extra == "doc"
Requires-Dist: docutils~=0.21; extra == "doc"
Requires-Dist: sphinx_design~=0.6.1; extra == "doc"
Requires-Dist: docutils_stubs~=0.0.22; extra == "doc"
Requires-Dist: sphinx_rtd_theme~=3.0; extra == "doc"
Provides-Extra: test
Requires-Dist: lxml~=5.4; extra == "test"
Requires-Dist: typing_extensions~=4.13; extra == "test"
Requires-Dist: pytest~=8.4; extra == "test"
Requires-Dist: Coverage~=7.8; extra == "test"
Requires-Dist: pyTooling<9.0,>=6.7; extra == "test"
Requires-Dist: mypy~=1.16; extra == "test"
Requires-Dist: pytest-cov~=6.1; extra == "test"
Requires-Dist: ruamel.yaml~=0.18; extra == "test"
Provides-Extra: all
Requires-Dist: lxml~=5.4; extra == "all"
Requires-Dist: sphinx~=8.2; extra == "all"
Requires-Dist: autoapi>=2.0.1; extra == "all"
Requires-Dist: sphinx_autodoc_typehints~=3.2; extra == "all"
Requires-Dist: typing_extensions~=4.13; extra == "all"
Requires-Dist: pytest~=8.4; extra == "all"
Requires-Dist: sphinx-copybutton>=0.5.2; extra == "all"
Requires-Dist: sphinx_reports~=0.9; extra == "all"
Requires-Dist: Coverage~=7.8; extra == "all"
Requires-Dist: pyTooling<9.0,>=6.7; extra == "all"
Requires-Dist: mypy~=1.16; extra == "all"
Requires-Dist: sphinxcontrib-mermaid~=1.0; extra == "all"
Requires-Dist: pytest-cov~=6.1; extra == "all"
Requires-Dist: ruamel.yaml~=0.18; extra == "all"
Requires-Dist: docutils~=0.21; extra == "all"
Requires-Dist: sphinx_design~=0.6.1; extra == "all"
Requires-Dist: docutils_stubs~=0.0.22; extra == "all"
Requires-Dist: sphinx_rtd_theme~=3.0; extra == "all"
Dynamic: author
Dynamic: author-email
Dynamic: classifier
Dynamic: description
Dynamic: description-content-type
Dynamic: home-page
Dynamic: keywords
Dynamic: license
Dynamic: license-file
Dynamic: project-url
Dynamic: provides-extra
Dynamic: requires-dist
Dynamic: requires-python
Dynamic: summary
